StatsArbPortfolio/StatsArbData.py
StatsArbPortfolio/StatsArbModels.py
StatsArbPortfolio/StatsArbPortfolio.py
StatsArbPortfolio/__init__.py
StatsArbPortfolio-1.0.4.dist-info/METADATA
StatsArbPortfolio-1.0.4.dist-info/WHEEL
StatsArbPortfolio-1.0.4.dist-info/top_level.txt
StatsArbPortfolio-1.0.4.dist-info/RECORD
