Metadata-Version: 2.1
Name: StatsArbPortfolio
Version: 1.0.4
Summary: StatsArbML
Home-page: UNKNOWN
Author: Carlos Gustavo Salas Flores
Author-email: cs582@duke.edu
License: MIT
Platform: UNKNOWN
Classifier: License :: OSI Approved :: MIT License
Classifier: Programming Language :: Python :: 3
Classifier: Programming Language :: Python :: 3.7
Requires-Dist: numpy
Requires-Dist: pandas
Requires-Dist: torch
Requires-Dist: sklearn
Requires-Dist: yfinance
Requires-Dist: matplotlib
